wtforms_json/__init__.py
WTForms_JSON-0.3.4.dist-info/LICENSE
WTForms_JSON-0.3.4.dist-info/METADATA
WTForms_JSON-0.3.4.dist-info/WHEEL
WTForms_JSON-0.3.4.dist-info/top_level.txt
WTForms_JSON-0.3.4.dist-info/RECORD
